examples/__init__.py
examples/autoencoder/__init__.py
examples/autoencoder/conv_autoencoder.py
examples/autoencoder/denoising_autoencoder.py
examples/autoencoder/stacked_conv_autoencoders.py
examples/autoencoder/variational_autoencoder.py
examples/competitive/__init__.py
examples/competitive/reduce_iris_sample_size_lvq.py
examples/competitive/sofm_basic.py
examples/competitive/sofm_compare_grid_types.py
examples/competitive/sofm_compare_weight_init.py
examples/competitive/sofm_digits.py
examples/competitive/sofm_heatmap_visualization.py
examples/competitive/sofm_iris_clustering.py
examples/competitive/sofm_moon_topology.py
examples/competitive/utils.py
neupy/__init__.py
neupy/environment.py
neupy/estimators.py
neupy/exceptions.py
neupy/init.py
neupy/storage.py
neupy/utils.py
neupy/algorithms/__init__.py
neupy/algorithms/base.py
neupy/algorithms/constructor.py
neupy/algorithms/plots.py
neupy/algorithms/rbm.py
neupy/algorithms/signals.py
neupy/algorithms/summary_info.py
neupy/algorithms/utils.py
neupy/algorithms/associative/__init__.py
neupy/algorithms/associative/base.py
neupy/algorithms/associative/hebb.py
neupy/algorithms/associative/instar.py
neupy/algorithms/associative/kohonen.py
neupy/algorithms/associative/oja.py
neupy/algorithms/competitive/__init__.py
neupy/algorithms/competitive/art.py
neupy/algorithms/competitive/growing_neural_gas.py
neupy/algorithms/competitive/lvq.py
neupy/algorithms/competitive/neighbours.py
neupy/algorithms/competitive/randomized_pca.py
neupy/algorithms/competitive/sofm.py
neupy/algorithms/ensemble/__init__.py
neupy/algorithms/ensemble/base.py
neupy/algorithms/ensemble/dan.py
neupy/algorithms/gd/__init__.py
neupy/algorithms/gd/adadelta.py
neupy/algorithms/gd/adagrad.py
neupy/algorithms/gd/adam.py
neupy/algorithms/gd/adamax.py
neupy/algorithms/gd/base.py
neupy/algorithms/gd/conjgrad.py
neupy/algorithms/gd/errors.py
neupy/algorithms/gd/hessdiag.py
neupy/algorithms/gd/hessian.py
neupy-0.8.2.dist-info/METADATA
neupy-0.8.2.dist-info/RECORD
neupy-0.8.2.dist-info/WHEEL
neupy-0.8.2.dist-info/top_level.txt
